bluemoss/__init__.py
bluemoss/scrape.py
bluemoss/classes/__init__.py
bluemoss/classes/extract.py
bluemoss/classes/jsonify.py
bluemoss/classes/node.py
bluemoss/classes/range.py
bluemoss/utils/__init__.py
bluemoss/utils/general.py
bluemoss/utils/html.py
bluemoss/utils/text.py
bluemoss/utils/url.py
bluemoss/utils/xpath.py
bluemoss-1.0.0.dist-info/LICENSE
bluemoss-1.0.0.dist-info/METADATA
bluemoss-1.0.0.dist-info/WHEEL
bluemoss-1.0.0.dist-info/top_level.txt
bluemoss-1.0.0.dist-info/RECORD
