Metadata-Version: 2.1
Name: bluemoss
Version: 1.0.0
Summary: bluemoss enables you to easily scrape websites.
Home-page: https://github.com/LucaTabone/bluemoss
Author: Luca Tabone
Author-email: luca@tabone.io
Maintainer: Luca Tabone
License: APACHE
Project-URL: Documentation, https://github.com/LucaTabone/bluemoss/blob/main/README.md
Project-URL: Source, https://github.com/LucaTabone/bluemoss
Project-URL: Tracker, https://github.com/LucaTabone/bluemoss/issues
Keywords: xpath,scrape,scraping,bluemoss,webscraping,web-scraping,recipe-scraping,template-scraping
Classifier: Development Status :: 4 - Beta
Classifier: Intended Audience :: Developers
Classifier: Typing :: Typed
Classifier: Topic :: Software Development :: Libraries
Classifier: Topic :: Software Development :: Libraries :: Python Modules
Classifier: Topic :: Internet
Classifier: Topic :: Internet :: WWW/HTTP
Classifier: Topic :: Text Processing
Classifier: Topic :: Text Processing :: Markup :: HTML
Classifier: Topic :: Text Processing :: Markup :: XML
Classifier: Topic :: Utilities
Classifier: Topic :: Scientific/Engineering :: Information Analysis
Classifier: Topic :: Internet :: WWW/HTTP :: Browsers
Classifier: Topic :: Internet :: WWW/HTTP :: Indexing/Search
Classifier: License :: OSI Approved :: Apache Software License
Classifier: Programming Language :: Python :: 3.9
Classifier: Programming Language :: Python :: 3.10
Classifier: Programming Language :: Python :: 3.11
Classifier: Programming Language :: Python :: 3.12
Classifier: Operating System :: POSIX
Classifier: Operating System :: MacOS
Classifier: Operating System :: POSIX :: Linux
Classifier: Operating System :: Microsoft :: Windows
Requires-Python: >=3.9.0
License-File: LICENSE
Requires-Dist: beautifulsoup4 ==4.12.2
Requires-Dist: lxml ==4.9.2 ; python_version == "3.10.*"
Requires-Dist: lxml ==4.9.1 ; python_version == "3.9.*"
Requires-Dist: lxml ==4.9.3 ; python_version >= "3.11"
